MySerializer/MySerializer.py
MySerializer/__init__.py
MySerializer/constants.py
MySerializer/json_utils.py
MySerializer/pack_utils.py
MySerializer/serializer.py
MySerializer/unpack_utils.py
MySerializer/xml_utils.py
SalatikSer-1.3.0.dist-info/METADATA
SalatikSer-1.3.0.dist-info/WHEEL
SalatikSer-1.3.0.dist-info/entry_points.txt
SalatikSer-1.3.0.dist-info/top_level.txt
SalatikSer-1.3.0.dist-info/RECORD
