Metadata-Version: 2.1
Name: SalatikSer
Version: 1.3.0
Summary: JSON and XLM serializer
Author: Daniil Litvinets
Author-email: salatik.dan@gmail.com
